url_location/__init__.py
url_location/service/URLLocation.py
url_location/service/__init__.py
url_location/utils/Countries.py
url_location/utils/Logger.py
url_location/utils/__init__.py
url_location-1.0.0b0.dist-info/LICENSE
url_location-1.0.0b0.dist-info/METADATA
url_location-1.0.0b0.dist-info/WHEEL
url_location-1.0.0b0.dist-info/top_level.txt
url_location-1.0.0b0.dist-info/RECORD
