Metadata-Version: 2.1
Name: url-location
Version: 1.0.0b0
Summary: Package to retrieve the iso 3 short code of the country to which a URL belongs
Home-page: https://github.com/....
Author: Eduardo Tuteggito Rosero
Author-email: zerhiphop@live.com
License: MIT License
Keywords: url,country,url_location
Platform: UNKNOWN
Classifier: Development Status :: 3 - Alpha
Classifier: Intended Audience :: Developers
Classifier: License :: OSI Approved :: MIT License
Classifier: Operating System :: OS Independent
Classifier: Programming Language :: Python :: 2
Classifier: Programming Language :: Python :: 2.7
Classifier: Programming Language :: Python :: 3
Classifier: Programming Language :: Python :: 3.4
Classifier: Programming Language :: Python :: 3.5
License-File: LICENSE
